LICENSE.txt
MANIFEST.in
README.md
setup.py
cache_tools/__init__.py
cache_tools/clearcache.py
cache_tools/models.py
cache_tools/precache.py
cache_tools/management/__init__.py
cache_tools/management/commands/__init__.py
cache_tools/management/commands/clearcache.py
cache_tools/management/commands/listurls.py
cache_tools/management/commands/precache.py
sisu_cache_tools.egg-info/PKG-INFO
sisu_cache_tools.egg-info/SOURCES.txt
sisu_cache_tools.egg-info/dependency_links.txt
sisu_cache_tools.egg-info/not-zip-safe
sisu_cache_tools.egg-info/top_level.txt