Metadata-Version: 1.1
Name: sisu-cache-tools
Version: 0.0.5
Summary: Management tools for managing the cache
Home-page: https://github.com/mkoistinen/sisu-cache-tools
Author: Martin Koistinen
Author-email: mkoistinen@gmail.com
License: LICENSE.txt
Download-URL: https://github.com/mkoistinen/sisu-cache-tools/tarball/0.0.1
Platform: OS Independent
Classifier: Development Status :: 5 - Production/Stable
Classifier: Environment :: Web Environment
Classifier: Framework :: Django
Classifier: Intended Audience :: Developers
Classifier: License :: OSI Approved :: BSD License
Classifier: Operating System :: OS Independent
Classifier: Programming Language :: Python
Classifier: Topic :: Communications
Classifier: Topic :: Internet :: WWW/HTTP :: Dynamic Content
Classifier: Programming Language :: Python :: 2.7
